{"name":"FdjaK","tagline":"","body":"<!DOCTYPE html>\r\n<html>\r\n  <head>\r\n    <meta name=\"viewport\" content=\"width=device-width, initial-scale=1\">\r\n    <link rel=\"stylesheet\" href=\"http://maxcdn.bootstrapcdn.com/bootstrap/3.2.0/css/bootstrap.min.css\">\r\n\r\n\r\n  </head>\r\n\r\n  <body>\r\n    <button type=\"button\"  class=\"btn btn-primary btn-lg\"  data-target=\"#myModal\">\r\n  Contact\r\n</button>\r\n <script type=\"text/javascript\" src=\"http://code.jquery.com/jquery-1.10.0.min.js\"></script>\r\n<script type=\"text/javascript\">\r\n\r\n\r\n$(\"button\").click(function(ev){\r\n  ev.preventDefault();\r\n\r\n  \r\n \r\n  console.log(\"aravind\");\r\n  $(\"#myModal\").modal(\"show\");\r\n\r\n  \r\n});\r\n\r\n\r\n</script>\r\n\r\n\r\n<div class=\"modal fade\" id=\"myModal\" >\r\n\r\n<div class=\"modal-dialog\">\r\n<div class=\"modal-content\">\r\n<div class=\"modal-header\">\r\n<button type=\"button\" class=\"closs\" data-dismiss=\"modal\">close</button>\r\n\r\n\r\n</div>\r\n<div class=\"modal-body\">\r\nWelcome to my first project<br>\r\n\r\n</div>\r\n<div class=\"modal-footer\">\r\n<button type=\"button\" class=\"btn btn-default\" data-dismiss=\"modal\">close</button>\r\n<button type=\"button\" class=\"btn btn-default\" >thanks</button>\r\n</div>\r\n\r\n\r\n</div>\r\n</div>\r\n</div>\r\n\r\n\r\n\r\n    \r\n    <script src=\"https://ajax.googleapis.com/ajax/libs/jquery/1.11.1/jquery.min.js\"></script>\r\n    <script src=\"http://maxcdn.bootstrapcdn.com/bootstrap/3.2.0/js/bootstrap.min.js\"></script>\r\n  </body>\r\n</html>","google":"","note":"Don't delete this file! It's used internally to help with page regeneration."}